chatx.py
chatx-0.0.1.dist-info/LICENSE
chatx-0.0.1.dist-info/WHEEL
chatx-0.0.1.dist-info/METADATA
chatx-0.0.1.dist-info/RECORD
